aeityper/__init__.py
aeityper/aeityper.py
aeityper-0.0.3.dist-info/METADATA
aeityper-0.0.3.dist-info/WHEEL
aeityper-0.0.3.dist-info/top_level.txt
aeityper-0.0.3.dist-info/RECORD
