Metadata-Version: 2.1
Name: aeityper
Version: 0.0.3
Summary: Typer. It types for you if pasting is disabled.
Author: Shreyanshu Malviya
Author-email: <shreyanshumalviya@gmail.com>
Keywords: type,write,paste
Classifier: Development Status :: 1 - Planning
Classifier: Intended Audience :: Developers
Classifier: Programming Language :: Python :: 3
Classifier: Operating System :: Unix
Classifier: Operating System :: MacOS :: MacOS X
Classifier: Operating System :: Microsoft :: Windows
Requires-Dist: keyboard
Requires-Dist: pyautogui
Requires-Dist: pyperclip
